{"id":"Task7","name":"משימה 7: הוספת בלוק מיוחד","data":{"root":{"children":[{"children":[{"detail":0,"format":0,"mode":"normal","style":"","text":"משימה 7: הוספת בלוק מיוחד","type":"text","version":1}],"direction":"rtl","format":"center","indent":0,"type":"heading","version":1,"tag":"h2"},{"children":[{"children":[{"detail":0,"format":0,"mode":"normal","style":"","text":"הוסף קשקוש אחרי שורה זו","type":"text","version":1}],"direction":"rtl","format":"","indent":0,"type":"listitem","version":1,"value":1}],"direction":"rtl","format":"","indent":0,"type":"list","version":1,"listType":"number","start":1,"tag":"ol"},{"children":[],"direction":"ltr","format":"","indent":0,"type":"paragraph","version":1},{"children":[{"children":[{"detail":0,"format":0,"mode":"normal","style":"","text":"הוסף קשקוש אחרי שורה זו","type":"text","version":1}],"direction":"rtl","format":"","indent":0,"type":"listitem","version":1,"value":2}],"direction":"rtl","format":"","indent":0,"type":"list","version":1,"listType":"number","start":2,"tag":"ol"},{"children":[],"direction":"ltr","format":"","indent":0,"type":"paragraph","version":1},{"children":[{"children":[{"detail":0,"format":0,"mode":"normal","style":"","text":"הוסף טבלה 4 על 4 אחרי שורה זו","type":"text","version":1}],"direction":"rtl","format":"","indent":0,"type":"listitem","version":1,"value":3}],"direction":"rtl","format":"","indent":0,"type":"list","version":1,"listType":"number","start":3,"tag":"ol"},{"children":[],"direction":"rtl","format":"","indent":0,"type":"paragraph","version":1}],"direction":"rtl","format":"","type":"root","version":1}}}